<?xml version="1.0"?>
<!-- edited with XMLSPY v2004 rel. 2 U (http://www.xmlspy.com) by Dean Ray Johnson (Firaxis Games) -->
<!-- Sid Meier's Civilization 4 -->
<!-- Copyright Firaxis Games 2005 -->
<!-- -->
<!-- AudioDefines -->
<AudioDefines xmlns="x-schema:Canada_AudioDefinesSchema.xml">
	<SoundDatas>
		<SoundData>
			<SoundID>SND_CANADA_SELECT</SoundID>
			<Filename>Modules/Custom_Civilizations_MCP/Canada/SelectOrder/CanadaSelect</Filename>
			<LoadType>DYNAMIC_RES</LoadType>
			<bIsCompressed>1</bIsCompressed>
			<bInGeneric>1</bInGeneric>
		</SoundData>
		<SoundData>
			<SoundID>SND_CANADA_ORDER</SoundID>
			<Filename>Modules/Custom_Civilizations_MCP/Canada/SelectOrder/CanadaOrder</Filename>
			<LoadType>DYNAMIC_RES</LoadType>
			<bIsCompressed>1</bIsCompressed>
			<bInGeneric>1</bInGeneric>
		</SoundData>
		<SoundData>
			<SoundID>DIPLO_JEAN_PEACE_ANCIENT</SoundID>
			<Filename>Modules/Custom_Civilizations_MCP/Canada/Soundpack/CANADA_PEACE_ANCIENT</Filename>
			<LoadType>STREAMED</LoadType>
			<bIsCompressed>1</bIsCompressed>
			<bInGeneric>1</bInGeneric>
		</SoundData>
		<SoundData>
			<SoundID>DIPLO_JEAN_PEACE_ANCIENT_INTRO</SoundID>
			<Filename>Modules/Custom_Civilizations_MCP/Canada/Soundpack/CANADA_PEACE_ANCIENT_INTRO</Filename>
			<LoadType>STREAMED</LoadType>
			<bIsCompressed>1</bIsCompressed>
			<bInGeneric>1</bInGeneric>
		</SoundData>
		<SoundData>
			<SoundID>DIPLO_JEAN_WAR_ANCIENT</SoundID>
			<Filename>Modules/Custom_Civilizations_MCP/Canada/Soundpack/CANADA_WAR_ANCIENT</Filename>
			<LoadType>STREAMED</LoadType>
			<bIsCompressed>1</bIsCompressed>
			<bInGeneric>1</bInGeneric>
		</SoundData>
		<SoundData>
			<SoundID>DIPLO_JEAN_WAR_ANCIENT_INTRO</SoundID>
			<Filename>Modules/Custom_Civilizations_MCP/Canada/Soundpack/CANADA_WAR_ANCIENT_INTRO</Filename>
			<LoadType>STREAMED</LoadType>
			<bIsCompressed>1</bIsCompressed>
			<bInGeneric>1</bInGeneric>
		</SoundData>
		<SoundData>
			<SoundID>DIPLO_JEAN_PEACE_CLASSICAL</SoundID>
			<Filename>Modules/Custom_Civilizations_MCP/Canada/Soundpack/CANADA_PEACE_CLASSICAL</Filename>
			<LoadType>STREAMED</LoadType>
			<bIsCompressed>1</bIsCompressed>
			<bInGeneric>1</bInGeneric>
		</SoundData>
		<SoundData>
			<SoundID>DIPLO_JEAN_PEACE_CLASSICAL_INTRO</SoundID>
			<Filename>Modules/Custom_Civilizations_MCP/Canada/Soundpack/CANADA_PEACE_CLASSICAL_INTRO</Filename>
			<LoadType>STREAMED</LoadType>
			<bIsCompressed>1</bIsCompressed>
			<bInGeneric>1</bInGeneric>
		</SoundData>
		<SoundData>
			<SoundID>DIPLO_JEAN_WAR_CLASSICAL</SoundID>
			<Filename>Modules/Custom_Civilizations_MCP/Canada/Soundpack/CANADA_WAR_CLASSICAL</Filename>
			<LoadType>STREAMED</LoadType>
			<bIsCompressed>1</bIsCompressed>
			<bInGeneric>1</bInGeneric>
		</SoundData>
		<SoundData>
			<SoundID>DIPLO_JEAN_WAR_CLASSICAL_INTRO</SoundID>
			<Filename>Modules/Custom_Civilizations_MCP/Canada/Soundpack/CANADA_WAR_CLASSICAL_INTRO</Filename>
			<LoadType>STREAMED</LoadType>
			<bIsCompressed>1</bIsCompressed>
			<bInGeneric>1</bInGeneric>
		</SoundData>
		<SoundData>
			<SoundID>DIPLO_JEAN_PEACE_MEDIEVAL</SoundID>
			<Filename>Modules/Custom_Civilizations_MCP/Canada/Soundpack/CANADA_PEACE_MEDIEVAL</Filename>
			<LoadType>STREAMED</LoadType>
			<bIsCompressed>1</bIsCompressed>
			<bInGeneric>1</bInGeneric>
		</SoundData>
		<SoundData>
			<SoundID>DIPLO_JEAN_PEACE_MEDIEVAL_INTRO</SoundID>
			<Filename>Modules/Custom_Civilizations_MCP/Canada/Soundpack/CANADA_PEACE_MEDIEVAL_INTRO</Filename>
			<LoadType>STREAMED</LoadType>
			<bIsCompressed>1</bIsCompressed>
			<bInGeneric>1</bInGeneric>
		</SoundData>
		<SoundData>
			<SoundID>DIPLO_JEAN_WAR_MEDIEVAL</SoundID>
			<Filename>Modules/Custom_Civilizations_MCP/Canada/Soundpack/CANADA_WAR_MEDIEVAL</Filename>
			<LoadType>STREAMED</LoadType>
			<bIsCompressed>1</bIsCompressed>
			<bInGeneric>1</bInGeneric>
		</SoundData>
		<SoundData>
			<SoundID>DIPLO_JEAN_WAR_MEDIEVAL_INTRO</SoundID>
			<Filename>Modules/Custom_Civilizations_MCP/Canada/Soundpack/CANADA_WAR_MEDIEVAL_INTRO</Filename>
			<LoadType>STREAMED</LoadType>
			<bIsCompressed>1</bIsCompressed>
			<bInGeneric>1</bInGeneric>
		</SoundData>
		<SoundData>
			<SoundID>DIPLO_JEAN_PEACE_RENAISSANCE</SoundID>
			<Filename>Modules/Custom_Civilizations_MCP/Canada/Soundpack/CANADA_PEACE_RENAISSANCE</Filename>
			<LoadType>STREAMED</LoadType>
			<bIsCompressed>1</bIsCompressed>
			<bInGeneric>1</bInGeneric>
		</SoundData>
		<SoundData>
			<SoundID>DIPLO_JEAN_PEACE_RENAISSANCE_INTRO</SoundID>
			<Filename>Modules/Custom_Civilizations_MCP/Canada/Soundpack/CANADA_PEACE_RENAISSANCE_INTRO</Filename>
			<LoadType>STREAMED</LoadType>
			<bIsCompressed>1</bIsCompressed>
			<bInGeneric>1</bInGeneric>
		</SoundData>
		<SoundData>
			<SoundID>DIPLO_JEAN_WAR_RENAISSANCE</SoundID>
			<Filename>Modules/Custom_Civilizations_MCP/Canada/Soundpack/CANADA_WAR_RENAISSANCE</Filename>
			<LoadType>STREAMED</LoadType>
			<bIsCompressed>1</bIsCompressed>
			<bInGeneric>1</bInGeneric>
		</SoundData>
		<SoundData>
			<SoundID>DIPLO_JEAN_WAR_RENAISSANCE_INTRO</SoundID>
			<Filename>Modules/Custom_Civilizations_MCP/Canada/Soundpack/CANADA_WAR_RENAISSANCE_INTRO</Filename>
			<LoadType>STREAMED</LoadType>
			<bIsCompressed>1</bIsCompressed>
			<bInGeneric>1</bInGeneric>
		</SoundData>
		<SoundData>
			<SoundID>DIPLO_JEAN_PEACE_INDUSTRIAL</SoundID>
			<Filename>Modules/Custom_Civilizations_MCP/Canada/Soundpack/CANADA_PEACE_INDUSTRIAL</Filename>
			<LoadType>STREAMED</LoadType>
			<bIsCompressed>1</bIsCompressed>
			<bInGeneric>1</bInGeneric>
		</SoundData>
		<SoundData>
			<SoundID>DIPLO_JEAN_PEACE_INDUSTRIAL_INTRO</SoundID>
			<Filename>Modules/Custom_Civilizations_MCP/Canada/Soundpack/CANADA_PEACE_INDUSTRIAL_INTRO</Filename>
			<LoadType>STREAMED</LoadType>
			<bIsCompressed>1</bIsCompressed>
			<bInGeneric>1</bInGeneric>
		</SoundData>
		<SoundData>
			<SoundID>DIPLO_JEAN_WAR_INDUSTRIAL</SoundID>
			<Filename>Modules/Custom_Civilizations_MCP/Canada/Soundpack/CANADA_WAR_INDUSTRIAL</Filename>
			<LoadType>STREAMED</LoadType>
			<bIsCompressed>1</bIsCompressed>
			<bInGeneric>1</bInGeneric>
		</SoundData>
		<SoundData>
			<SoundID>DIPLO_JEAN_WAR_INDUSTRIAL_INTRO</SoundID>
			<Filename>Modules/Custom_Civilizations_MCP/Canada/Soundpack/CANADA_WAR_INDUSTRIAL_INTRO</Filename>
			<LoadType>STREAMED</LoadType>
			<bIsCompressed>1</bIsCompressed>
			<bInGeneric>1</bInGeneric>
		</SoundData>
		<SoundData>
			<SoundID>DIPLO_JEAN_PEACE_MODERN</SoundID>
			<Filename>Modules/Custom_Civilizations_MCP/Canada/Soundpack/CANADA_PEACE_MODERN</Filename>
			<LoadType>STREAMED</LoadType>
			<bIsCompressed>1</bIsCompressed>
			<bInGeneric>1</bInGeneric>
		</SoundData>
		<SoundData>
			<SoundID>DIPLO_JEAN_PEACE_MODERN_INTRO</SoundID>
			<Filename>Modules/Custom_Civilizations_MCP/Canada/Soundpack/CANADA_PEACE_MODERN_INTRO</Filename>
			<LoadType>STREAMED</LoadType>
			<bIsCompressed>1</bIsCompressed>
			<bInGeneric>1</bInGeneric>
		</SoundData>
		<SoundData>
			<SoundID>DIPLO_JEAN_WAR_MODERN</SoundID>
			<Filename>Modules/Custom_Civilizations_MCP/Canada/Soundpack/CANADA_WAR_MODERN</Filename>
			<LoadType>STREAMED</LoadType>
			<bIsCompressed>1</bIsCompressed>
			<bInGeneric>1</bInGeneric>
		</SoundData>
		<SoundData>
			<SoundID>DIPLO_JEAN_WAR_MODERN_INTRO</SoundID>
			<Filename>Modules/Custom_Civilizations_MCP/Canada/Soundpack/CANADA_WAR_MODERN_INTRO</Filename>
			<LoadType>STREAMED</LoadType>
			<bIsCompressed>1</bIsCompressed>
			<bInGeneric>1</bInGeneric>
		</SoundData>
		<SoundData>
			<SoundID>DIPLO_JEAN_PEACE_FUTURE</SoundID>
			<Filename>Modules/Custom_Civilizations_MCP/Canada/Soundpack/CANADA_PEACE_FUTURE</Filename>
			<LoadType>STREAMED</LoadType>
			<bIsCompressed>1</bIsCompressed>
			<bInGeneric>1</bInGeneric>
		</SoundData>
		<SoundData>
			<SoundID>DIPLO_JEAN_PEACE_FUTURE_INTRO</SoundID>
			<Filename>Modules/Custom_Civilizations_MCP/Canada/Soundpack/CANADA_PEACE_FUTURE_INTRO</Filename>
			<LoadType>STREAMED</LoadType>
			<bIsCompressed>1</bIsCompressed>
			<bInGeneric>1</bInGeneric>
		</SoundData>
		<SoundData>
			<SoundID>DIPLO_JEAN_WAR_FUTURE</SoundID>
			<Filename>Modules/Custom_Civilizations_MCP/Canada/Soundpack/CANADA_WAR_FUTURE</Filename>
			<LoadType>STREAMED</LoadType>
			<bIsCompressed>1</bIsCompressed>
			<bInGeneric>1</bInGeneric>
		</SoundData>
		<SoundData>
			<SoundID>DIPLO_JEAN_WAR_FUTURE_INTRO</SoundID>
			<Filename>Modules/Custom_Civilizations_MCP/Canada/Soundpack/CANADA_WAR_FUTURE_INTRO</Filename>
			<LoadType>STREAMED</LoadType>
			<bIsCompressed>1</bIsCompressed>
			<bInGeneric>1</bInGeneric>
		</SoundData>
		<SoundData>
			<SoundID>DIPLO_MACDONALD_PEACE_ANCIENT</SoundID>
			<Filename>Modules/Custom_Civilizations_MCP/Canada/Soundpack/CANADA_Peace_Ancient</Filename>
			<LoadType>STREAMED</LoadType>
			<bIsCompressed>1</bIsCompressed>
			<bInGeneric>1</bInGeneric>
		</SoundData>
		<SoundData>
			<SoundID>DIPLO_MACDONALD_PEACE_ANCIENT_INTRO</SoundID>
			<Filename>Modules/Custom_Civilizations_MCP/Canada/Soundpack/CANADA_Peace_Ancient_Intro</Filename>
			<LoadType>STREAMED</LoadType>
			<bIsCompressed>1</bIsCompressed>
			<bInGeneric>1</bInGeneric>
		</SoundData>
		<SoundData>
			<SoundID>DIPLO_MACDONALD_WAR_ANCIENT</SoundID>
			<Filename>Modules/Custom_Civilizations_MCP/Canada/Soundpack/CANADA_WAR_ANCIENT</Filename>
			<LoadType>STREAMED</LoadType>
			<bIsCompressed>1</bIsCompressed>
			<bInGeneric>1</bInGeneric>
		</SoundData>
		<SoundData>
			<SoundID>DIPLO_MACDONALD_WAR_ANCIENT_INTRO</SoundID>
			<Filename>Modules/Custom_Civilizations_MCP/Canada/Soundpack/CANADA_WAR_ANCIENT_INTRO</Filename>
			<LoadType>STREAMED</LoadType>
			<bIsCompressed>1</bIsCompressed>
			<bInGeneric>1</bInGeneric>
		</SoundData>
		<SoundData>
			<SoundID>DIPLO_MACDONALD_PEACE_CLASSICAL</SoundID>
			<Filename>Modules/Custom_Civilizations_MCP/Canada/Soundpack/CANADA_PEACE_CLASSICAL</Filename>
			<LoadType>STREAMED</LoadType>
			<bIsCompressed>1</bIsCompressed>
			<bInGeneric>1</bInGeneric>
		</SoundData>
		<SoundData>
			<SoundID>DIPLO_MACDONALD_PEACE_CLASSICAL_INTRO</SoundID>
			<Filename>Modules/Custom_Civilizations_MCP/Canada/Soundpack/CANADA_PEACE_CLASSICAL_INTRO</Filename>
			<LoadType>STREAMED</LoadType>
			<bIsCompressed>1</bIsCompressed>
			<bInGeneric>1</bInGeneric>
		</SoundData>
		<SoundData>
			<SoundID>DIPLO_MACDONALD_WAR_CLASSICAL</SoundID>
			<Filename>Modules/Custom_Civilizations_MCP/Canada/Soundpack/CANADA_WAR_CLASSICAL</Filename>
			<LoadType>STREAMED</LoadType>
			<bIsCompressed>1</bIsCompressed>
			<bInGeneric>1</bInGeneric>
		</SoundData>
		<SoundData>
			<SoundID>DIPLO_MACDONALD_WAR_CLASSICAL_INTRO</SoundID>
			<Filename>Modules/Custom_Civilizations_MCP/Canada/Soundpack/CANADA_WAR_CLASSICAL_INTRO</Filename>
			<LoadType>STREAMED</LoadType>
			<bIsCompressed>1</bIsCompressed>
			<bInGeneric>1</bInGeneric>
		</SoundData>
		<SoundData>
			<SoundID>DIPLO_MACDONALD_PEACE_MEDIEVAL</SoundID>
			<Filename>Modules/Custom_Civilizations_MCP/Canada/Soundpack/CANADA_PEACE_MEDIEVAL</Filename>
			<LoadType>STREAMED</LoadType>
			<bIsCompressed>1</bIsCompressed>
			<bInGeneric>1</bInGeneric>
		</SoundData>
		<SoundData>
			<SoundID>DIPLO_MACDONALD_PEACE_MEDIEVAL_INTRO</SoundID>
			<Filename>Modules/Custom_Civilizations_MCP/Canada/Soundpack/CANADA_PEACE_MEDIEVAL_INTRO</Filename>
			<LoadType>STREAMED</LoadType>
			<bIsCompressed>1</bIsCompressed>
			<bInGeneric>1</bInGeneric>
		</SoundData>
		<SoundData>
			<SoundID>DIPLO_MACDONALD_WAR_MEDIEVAL</SoundID>
			<Filename>Modules/Custom_Civilizations_MCP/Canada/Soundpack/CANADA_WAR_MEDIEVAL</Filename>
			<LoadType>STREAMED</LoadType>
			<bIsCompressed>1</bIsCompressed>
			<bInGeneric>1</bInGeneric>
		</SoundData>
		<SoundData>
			<SoundID>DIPLO_MACDONALD_WAR_MEDIEVAL_INTRO</SoundID>
			<Filename>Modules/Custom_Civilizations_MCP/Canada/Soundpack/CANADA_WAR_MEDIEVAL_INTRO</Filename>
			<LoadType>STREAMED</LoadType>
			<bIsCompressed>1</bIsCompressed>
			<bInGeneric>1</bInGeneric>
		</SoundData>
		<SoundData>
			<SoundID>DIPLO_MACDONALD_PEACE_RENAISSANCE</SoundID>
			<Filename>Modules/Custom_Civilizations_MCP/Canada/Soundpack/CANADA_PEACE_RENAISSANCE</Filename>
			<LoadType>STREAMED</LoadType>
			<bIsCompressed>1</bIsCompressed>
			<bInGeneric>1</bInGeneric>
		</SoundData>
		<SoundData>
			<SoundID>DIPLO_MACDONALD_PEACE_RENAISSANCE_INTRO</SoundID>
			<Filename>Modules/Custom_Civilizations_MCP/Canada/Soundpack/CANADA_PEACE_RENAISSANCE_INTRO</Filename>
			<LoadType>STREAMED</LoadType>
			<bIsCompressed>1</bIsCompressed>
			<bInGeneric>1</bInGeneric>
		</SoundData>
		<SoundData>
			<SoundID>DIPLO_MACDONALD_WAR_RENAISSANCE</SoundID>
			<Filename>Modules/Custom_Civilizations_MCP/Canada/Soundpack/CANADA_WAR_RENAISSANCE</Filename>
			<LoadType>STREAMED</LoadType>
			<bIsCompressed>1</bIsCompressed>
			<bInGeneric>1</bInGeneric>
		</SoundData>
		<SoundData>
			<SoundID>DIPLO_MACDONALD_WAR_RENAISSANCE_INTRO</SoundID>
			<Filename>Modules/Custom_Civilizations_MCP/Canada/Soundpack/CANADA_WAR_RENAISSANCE_INTRO</Filename>
			<LoadType>STREAMED</LoadType>
			<bIsCompressed>1</bIsCompressed>
			<bInGeneric>1</bInGeneric>
		</SoundData>
		<SoundData>
			<SoundID>DIPLO_MACDONALD_PEACE_INDUSTRIAL</SoundID>
			<Filename>Modules/Custom_Civilizations_MCP/Canada/Soundpack/CANADA_PEACE_INDUSTRIAL</Filename>
			<LoadType>STREAMED</LoadType>
			<bIsCompressed>1</bIsCompressed>
			<bInGeneric>1</bInGeneric>
		</SoundData>
		<SoundData>
			<SoundID>DIPLO_MACDONALD_PEACE_INDUSTRIAL_INTRO</SoundID>
			<Filename>Modules/Custom_Civilizations_MCP/Canada/Soundpack/CANADA_PEACE_INDUSTRIAL_INTRO</Filename>
			<LoadType>STREAMED</LoadType>
			<bIsCompressed>1</bIsCompressed>
			<bInGeneric>1</bInGeneric>
		</SoundData>
		<SoundData>
			<SoundID>DIPLO_MACDONALD_WAR_INDUSTRIAL</SoundID>
			<Filename>Modules/Custom_Civilizations_MCP/Canada/Soundpack/CANADA_WAR_INDUSTRIAL</Filename>
			<LoadType>STREAMED</LoadType>
			<bIsCompressed>1</bIsCompressed>
			<bInGeneric>1</bInGeneric>
		</SoundData>
		<SoundData>
			<SoundID>DIPLO_MACDONALD_WAR_INDUSTRIAL_INTRO</SoundID>
			<Filename>Modules/Custom_Civilizations_MCP/Canada/Soundpack/CANADA_WAR_INDUSTRIAL_INTRO</Filename>
			<LoadType>STREAMED</LoadType>
			<bIsCompressed>1</bIsCompressed>
			<bInGeneric>1</bInGeneric>
		</SoundData>
		<SoundData>
			<SoundID>DIPLO_MACDONALD_PEACE_MODERN</SoundID>
			<Filename>Modules/Custom_Civilizations_MCP/Canada/Soundpack/CANADA_PEACE_MODERN</Filename>
			<LoadType>STREAMED</LoadType>
			<bIsCompressed>1</bIsCompressed>
			<bInGeneric>1</bInGeneric>
		</SoundData>
		<SoundData>
			<SoundID>DIPLO_MACDONALD_PEACE_MODERN_INTRO</SoundID>
			<Filename>Modules/Custom_Civilizations_MCP/Canada/Soundpack/CANADA_PEACE_MODERN_INTRO</Filename>
			<LoadType>STREAMED</LoadType>
			<bIsCompressed>1</bIsCompressed>
			<bInGeneric>1</bInGeneric>
		</SoundData>
		<SoundData>
			<SoundID>DIPLO_MACDONALD_WAR_MODERN</SoundID>
			<Filename>Modules/Custom_Civilizations_MCP/Canada/Soundpack/CANADA_WAR_MODERN</Filename>
			<LoadType>STREAMED</LoadType>
			<bIsCompressed>1</bIsCompressed>
			<bInGeneric>1</bInGeneric>
		</SoundData>
		<SoundData>
			<SoundID>DIPLO_MACDONALD_WAR_MODERN_INTRO</SoundID>
			<Filename>Modules/Custom_Civilizations_MCP/Canada/Soundpack/CANADA_WAR_MODERN_INTRO</Filename>
			<LoadType>STREAMED</LoadType>
			<bIsCompressed>1</bIsCompressed>
			<bInGeneric>1</bInGeneric>
		</SoundData>
		<SoundData>
			<SoundID>DIPLO_MACDONALD_PEACE_FUTURE</SoundID>
			<Filename>Modules/Custom_Civilizations_MCP/Canada/Soundpack/CANADA_PEACE_FUTURE</Filename>
			<LoadType>STREAMED</LoadType>
			<bIsCompressed>1</bIsCompressed>
			<bInGeneric>1</bInGeneric>
		</SoundData>
		<SoundData>
			<SoundID>DIPLO_MACDONALD_PEACE_FUTURE_INTRO</SoundID>
			<Filename>Modules/Custom_Civilizations_MCP/Canada/Soundpack/CANADA_PEACE_FUTURE_INTRO</Filename>
			<LoadType>STREAMED</LoadType>
			<bIsCompressed>1</bIsCompressed>
			<bInGeneric>1</bInGeneric>
		</SoundData>
		<SoundData>
			<SoundID>DIPLO_MACDONALD_WAR_FUTURE</SoundID>
			<Filename>Modules/Custom_Civilizations_MCP/Canada/Soundpack/CANADA_WAR_FUTURE</Filename>
			<LoadType>STREAMED</LoadType>
			<bIsCompressed>1</bIsCompressed>
			<bInGeneric>1</bInGeneric>
		</SoundData>
		<SoundData>
			<SoundID>DIPLO_MACDONALD_WAR_FUTURE_INTRO</SoundID>
			<Filename>Modules/Custom_Civilizations_MCP/Canada/Soundpack/CANADA_WAR_FUTURE_INTRO</Filename>
			<LoadType>STREAMED</LoadType>
			<bIsCompressed>1</bIsCompressed>
			<bInGeneric>1</bInGeneric>
		</SoundData>
		<SoundData>
			<SoundID>DIPLO_MACKENZIEKING_PEACE_ANCIENT</SoundID>
			<Filename>Modules/Custom_Civilizations_MCP/Canada/Soundpack/CANADA_PEACE_ANCIENT</Filename>
			<LoadType>STREAMED</LoadType>
			<bIsCompressed>1</bIsCompressed>
			<bInGeneric>1</bInGeneric>
		</SoundData>
		<SoundData>
			<SoundID>DIPLO_MACKENZIEKING_PEACE_ANCIENT_INTRO</SoundID>
			<Filename>Modules/Custom_Civilizations_MCP/Canada/Soundpack/CANADA_PEACE_ANCIENT_INTRO</Filename>
			<LoadType>STREAMED</LoadType>
			<bIsCompressed>1</bIsCompressed>
			<bInGeneric>1</bInGeneric>
		</SoundData>
		<SoundData>
			<SoundID>DIPLO_MACKENZIEKING_WAR_ANCIENT</SoundID>
			<Filename>Modules/Custom_Civilizations_MCP/Canada/Soundpack/CANADA_WAR_ANCIENT</Filename>
			<LoadType>STREAMED</LoadType>
			<bIsCompressed>1</bIsCompressed>
			<bInGeneric>1</bInGeneric>
		</SoundData>
		<SoundData>
			<SoundID>DIPLO_MACKENZIEKING_WAR_ANCIENT_INTRO</SoundID>
			<Filename>Modules/Custom_Civilizations_MCP/Canada/Soundpack/CANADA_WAR_ANCIENT_INTRO</Filename>
			<LoadType>STREAMED</LoadType>
			<bIsCompressed>1</bIsCompressed>
			<bInGeneric>1</bInGeneric>
		</SoundData>
		<SoundData>
			<SoundID>DIPLO_MACKENZIEKING_PEACE_CLASSICAL</SoundID>
			<Filename>Modules/Custom_Civilizations_MCP/Canada/Soundpack/CANADA_PEACE_CLASSICAL</Filename>
			<LoadType>STREAMED</LoadType>
			<bIsCompressed>1</bIsCompressed>
			<bInGeneric>1</bInGeneric>
		</SoundData>
		<SoundData>
			<SoundID>DIPLO_MACKENZIEKING_PEACE_CLASSICAL_INTRO</SoundID>
			<Filename>Modules/Custom_Civilizations_MCP/Canada/Soundpack/CANADA_PEACE_CLASSICAL_INTRO</Filename>
			<LoadType>STREAMED</LoadType>
			<bIsCompressed>1</bIsCompressed>
			<bInGeneric>1</bInGeneric>
		</SoundData>
		<SoundData>
			<SoundID>DIPLO_MACKENZIEKING_WAR_CLASSICAL</SoundID>
			<Filename>Modules/Custom_Civilizations_MCP/Canada/Soundpack/CANADA_WAR_CLASSICAL</Filename>
			<LoadType>STREAMED</LoadType>
			<bIsCompressed>1</bIsCompressed>
			<bInGeneric>1</bInGeneric>
		</SoundData>
		<SoundData>
			<SoundID>DIPLO_MACKENZIEKING_WAR_CLASSICAL_INTRO</SoundID>
			<Filename>Modules/Custom_Civilizations_MCP/Canada/Soundpack/CANADA_WAR_CLASSICAL_INTRO</Filename>
			<LoadType>STREAMED</LoadType>
			<bIsCompressed>1</bIsCompressed>
			<bInGeneric>1</bInGeneric>
		</SoundData>
		<SoundData>
			<SoundID>DIPLO_MACKENZIEKING_PEACE_MEDIEVAL</SoundID>
			<Filename>Modules/Custom_Civilizations_MCP/Canada/Soundpack/CANADA_PEACE_MEDIEVAL</Filename>
			<LoadType>STREAMED</LoadType>
			<bIsCompressed>1</bIsCompressed>
			<bInGeneric>1</bInGeneric>
		</SoundData>
		<SoundData>
			<SoundID>DIPLO_MACKENZIEKING_PEACE_MEDIEVAL_INTRO</SoundID>
			<Filename>Modules/Custom_Civilizations_MCP/Canada/Soundpack/CANADA_PEACE_MEDIEVAL_INTRO</Filename>
			<LoadType>STREAMED</LoadType>
			<bIsCompressed>1</bIsCompressed>
			<bInGeneric>1</bInGeneric>
		</SoundData>
		<SoundData>
			<SoundID>DIPLO_MACKENZIEKING_WAR_MEDIEVAL</SoundID>
			<Filename>Modules/Custom_Civilizations_MCP/Canada/Soundpack/CANADA_WAR_MEDIEVAL</Filename>
			<LoadType>STREAMED</LoadType>
			<bIsCompressed>1</bIsCompressed>
			<bInGeneric>1</bInGeneric>
		</SoundData>
		<SoundData>
			<SoundID>DIPLO_MACKENZIEKING_WAR_MEDIEVAL_INTRO</SoundID>
			<Filename>Modules/Custom_Civilizations_MCP/Canada/Soundpack/CANADA_WAR_MEDIEVAL_INTRO</Filename>
			<LoadType>STREAMED</LoadType>
			<bIsCompressed>1</bIsCompressed>
			<bInGeneric>1</bInGeneric>
		</SoundData>
		<SoundData>
			<SoundID>DIPLO_MACKENZIEKING_PEACE_RENAISSANCE</SoundID>
			<Filename>Modules/Custom_Civilizations_MCP/Canada/Soundpack/CANADA_PEACE_RENAISSANCE</Filename>
			<LoadType>STREAMED</LoadType>
			<bIsCompressed>1</bIsCompressed>
			<bInGeneric>1</bInGeneric>
		</SoundData>
		<SoundData>
			<SoundID>DIPLO_MACKENZIEKING_PEACE_RENAISSANCE_INTRO</SoundID>
			<Filename>Modules/Custom_Civilizations_MCP/Canada/Soundpack/CANADA_PEACE_RENAISSANCE_INTRO</Filename>
			<LoadType>STREAMED</LoadType>
			<bIsCompressed>1</bIsCompressed>
			<bInGeneric>1</bInGeneric>
		</SoundData>
		<SoundData>
			<SoundID>DIPLO_MACKENZIEKING_WAR_RENAISSANCE</SoundID>
			<Filename>Modules/Custom_Civilizations_MCP/Canada/Soundpack/CANADA_WAR_RENAISSANCE</Filename>
			<LoadType>STREAMED</LoadType>
			<bIsCompressed>1</bIsCompressed>
			<bInGeneric>1</bInGeneric>
		</SoundData>
		<SoundData>
			<SoundID>DIPLO_MACKENZIEKING_WAR_RENAISSANCE_INTRO</SoundID>
			<Filename>Modules/Custom_Civilizations_MCP/Canada/Soundpack/CANADA_WAR_RENAISSANCE_INTRO</Filename>
			<LoadType>STREAMED</LoadType>
			<bIsCompressed>1</bIsCompressed>
			<bInGeneric>1</bInGeneric>
		</SoundData>
		<SoundData>
			<SoundID>DIPLO_MACKENZIEKING_PEACE_INDUSTRIAL</SoundID>
			<Filename>Modules/Custom_Civilizations_MCP/Canada/Soundpack/CANADA_PEACE_INDUSTRIAL</Filename>
			<LoadType>STREAMED</LoadType>
			<bIsCompressed>1</bIsCompressed>
			<bInGeneric>1</bInGeneric>
		</SoundData>
		<SoundData>
			<SoundID>DIPLO_MACKENZIEKING_PEACE_INDUSTRIAL_INTRO</SoundID>
			<Filename>Modules/Custom_Civilizations_MCP/Canada/Soundpack/CANADA_PEACE_INDUSTRIAL_INTRO</Filename>
			<LoadType>STREAMED</LoadType>
			<bIsCompressed>1</bIsCompressed>
			<bInGeneric>1</bInGeneric>
		</SoundData>
		<SoundData>
			<SoundID>DIPLO_MACKENZIEKING_WAR_INDUSTRIAL</SoundID>
			<Filename>Modules/Custom_Civilizations_MCP/Canada/Soundpack/CANADA_WAR_INDUSTRIAL</Filename>
			<LoadType>STREAMED</LoadType>
			<bIsCompressed>1</bIsCompressed>
			<bInGeneric>1</bInGeneric>
		</SoundData>
		<SoundData>
			<SoundID>DIPLO_MACKENZIEKING_WAR_INDUSTRIAL_INTRO</SoundID>
			<Filename>Modules/Custom_Civilizations_MCP/Canada/Soundpack/CANADA_WAR_INDUSTRIAL_INTRO</Filename>
			<LoadType>STREAMED</LoadType>
			<bIsCompressed>1</bIsCompressed>
			<bInGeneric>1</bInGeneric>
		</SoundData>
		<SoundData>
			<SoundID>DIPLO_MACKENZIEKING_PEACE_MODERN</SoundID>
			<Filename>Modules/Custom_Civilizations_MCP/Canada/Soundpack/CANADA_PEACE_MODERN</Filename>
			<LoadType>STREAMED</LoadType>
			<bIsCompressed>1</bIsCompressed>
			<bInGeneric>1</bInGeneric>
		</SoundData>
		<SoundData>
			<SoundID>DIPLO_MACKENZIEKING_PEACE_MODERN_INTRO</SoundID>
			<Filename>Modules/Custom_Civilizations_MCP/Canada/Soundpack/CANADA_PEACE_MODERN_INTRO</Filename>
			<LoadType>STREAMED</LoadType>
			<bIsCompressed>1</bIsCompressed>
			<bInGeneric>1</bInGeneric>
		</SoundData>
		<SoundData>
			<SoundID>DIPLO_MACKENZIEKING_WAR_MODERN</SoundID>
			<Filename>Modules/Custom_Civilizations_MCP/Canada/Soundpack/CANADA_WAR_MODERN</Filename>
			<LoadType>STREAMED</LoadType>
			<bIsCompressed>1</bIsCompressed>
			<bInGeneric>1</bInGeneric>
		</SoundData>
		<SoundData>
			<SoundID>DIPLO_MACKENZIEKING_WAR_MODERN_INTRO</SoundID>
			<Filename>Modules/Custom_Civilizations_MCP/Canada/Soundpack/CANADA_WAR_MODERN_INTRO</Filename>
			<LoadType>STREAMED</LoadType>
			<bIsCompressed>1</bIsCompressed>
			<bInGeneric>1</bInGeneric>
		</SoundData>
		<SoundData>
			<SoundID>DIPLO_MACKENZIEKING_PEACE_FUTURE</SoundID>
			<Filename>Modules/Custom_Civilizations_MCP/Canada/Soundpack/CANADA_PEACE_FUTURE</Filename>
			<LoadType>STREAMED</LoadType>
			<bIsCompressed>1</bIsCompressed>
			<bInGeneric>1</bInGeneric>
		</SoundData>
		<SoundData>
			<SoundID>DIPLO_MACKENZIEKING_PEACE_FUTURE_INTRO</SoundID>
			<Filename>Modules/Custom_Civilizations_MCP/Canada/Soundpack/CANADA_PEACE_FUTURE_INTRO</Filename>
			<LoadType>STREAMED</LoadType>
			<bIsCompressed>1</bIsCompressed>
			<bInGeneric>1</bInGeneric>
		</SoundData>
		<SoundData>
			<SoundID>DIPLO_MACKENZIEKING_WAR_FUTURE</SoundID>
			<Filename>Modules/Custom_Civilizations_MCP/Canada/Soundpack/CANADA_WAR_FUTURE</Filename>
			<LoadType>STREAMED</LoadType>
			<bIsCompressed>1</bIsCompressed>
			<bInGeneric>1</bInGeneric>
		</SoundData>
		<SoundData>
			<SoundID>DIPLO_MACKENZIEKING_WAR_FUTURE_INTRO</SoundID>
			<Filename>Modules/Custom_Civilizations_MCP/Canada/Soundpack/CANADA_WAR_FUTURE_INTRO</Filename>
			<LoadType>STREAMED</LoadType>
			<bIsCompressed>1</bIsCompressed>
			<bInGeneric>1</bInGeneric>
		</SoundData>
		<SoundData>
			<SoundID>DIPLO_PEARSON_PEACE_ANCIENT</SoundID>
			<Filename>Modules/Custom_Civilizations_MCP/Canada/Soundpack/CANADA_PEACE_ANCIENT</Filename>
			<LoadType>STREAMED</LoadType>
			<bIsCompressed>1</bIsCompressed>
			<bInGeneric>1</bInGeneric>
		</SoundData>
		<SoundData>
			<SoundID>DIPLO_PEARSON_PEACE_ANCIENT_INTRO</SoundID>
			<Filename>Modules/Custom_Civilizations_MCP/Canada/Soundpack/CANADA_PEACE_ANCIENT_INTRO</Filename>
			<LoadType>STREAMED</LoadType>
			<bIsCompressed>1</bIsCompressed>
			<bInGeneric>1</bInGeneric>
		</SoundData>
		<SoundData>
			<SoundID>DIPLO_PEARSON_WAR_ANCIENT</SoundID>
			<Filename>Modules/Custom_Civilizations_MCP/Canada/Soundpack/CANADA_WAR_ANCIENT</Filename>
			<LoadType>STREAMED</LoadType>
			<bIsCompressed>1</bIsCompressed>
			<bInGeneric>1</bInGeneric>
		</SoundData>
		<SoundData>
			<SoundID>DIPLO_PEARSON_WAR_ANCIENT_INTRO</SoundID>
			<Filename>Modules/Custom_Civilizations_MCP/Canada/Soundpack/CANADA_WAR_ANCIENT_INTRO</Filename>
			<LoadType>STREAMED</LoadType>
			<bIsCompressed>1</bIsCompressed>
			<bInGeneric>1</bInGeneric>
		</SoundData>
		<SoundData>
			<SoundID>DIPLO_PEARSON_PEACE_CLASSICAL</SoundID>
			<Filename>Modules/Custom_Civilizations_MCP/Canada/Soundpack/CANADA_PEACE_CLASSICAL</Filename>
			<LoadType>STREAMED</LoadType>
			<bIsCompressed>1</bIsCompressed>
			<bInGeneric>1</bInGeneric>
		</SoundData>
		<SoundData>
			<SoundID>DIPLO_PEARSON_PEACE_CLASSICAL_INTRO</SoundID>
			<Filename>Modules/Custom_Civilizations_MCP/Canada/Soundpack/CANADA_PEACE_CLASSICAL_INTRO</Filename>
			<LoadType>STREAMED</LoadType>
			<bIsCompressed>1</bIsCompressed>
			<bInGeneric>1</bInGeneric>
		</SoundData>
		<SoundData>
			<SoundID>DIPLO_PEARSON_WAR_CLASSICAL</SoundID>
			<Filename>Modules/Custom_Civilizations_MCP/Canada/Soundpack/CANADA_WAR_CLASSICAL</Filename>
			<LoadType>STREAMED</LoadType>
			<bIsCompressed>1</bIsCompressed>
			<bInGeneric>1</bInGeneric>
		</SoundData>
		<SoundData>
			<SoundID>DIPLO_PEARSON_WAR_CLASSICAL_INTRO</SoundID>
			<Filename>Modules/Custom_Civilizations_MCP/Canada/Soundpack/CANADA_WAR_CLASSICAL_INTRO</Filename>
			<LoadType>STREAMED</LoadType>
			<bIsCompressed>1</bIsCompressed>
			<bInGeneric>1</bInGeneric>
		</SoundData>
		<SoundData>
			<SoundID>DIPLO_PEARSON_PEACE_MEDIEVAL</SoundID>
			<Filename>Modules/Custom_Civilizations_MCP/Canada/Soundpack/CANADA_PEACE_MEDIEVAL</Filename>
			<LoadType>STREAMED</LoadType>
			<bIsCompressed>1</bIsCompressed>
			<bInGeneric>1</bInGeneric>
		</SoundData>
		<SoundData>
			<SoundID>DIPLO_PEARSON_PEACE_MEDIEVAL_INTRO</SoundID>
			<Filename>Modules/Custom_Civilizations_MCP/Canada/Soundpack/CANADA_PEACE_MEDIEVAL_INTRO</Filename>
			<LoadType>STREAMED</LoadType>
			<bIsCompressed>1</bIsCompressed>
			<bInGeneric>1</bInGeneric>
		</SoundData>
		<SoundData>
			<SoundID>DIPLO_PEARSON_WAR_MEDIEVAL</SoundID>
			<Filename>Modules/Custom_Civilizations_MCP/Canada/Soundpack/CANADA_WAR_MEDIEVAL</Filename>
			<LoadType>STREAMED</LoadType>
			<bIsCompressed>1</bIsCompressed>
			<bInGeneric>1</bInGeneric>
		</SoundData>
		<SoundData>
			<SoundID>DIPLO_PEARSON_WAR_MEDIEVAL_INTRO</SoundID>
			<Filename>Modules/Custom_Civilizations_MCP/Canada/Soundpack/CANADA_WAR_MEDIEVAL_INTRO</Filename>
			<LoadType>STREAMED</LoadType>
			<bIsCompressed>1</bIsCompressed>
			<bInGeneric>1</bInGeneric>
		</SoundData>
		<SoundData>
			<SoundID>DIPLO_PEARSON_PEACE_RENAISSANCE</SoundID>
			<Filename>Modules/Custom_Civilizations_MCP/Canada/Soundpack/CANADA_PEACE_RENAISSANCE</Filename>
			<LoadType>STREAMED</LoadType>
			<bIsCompressed>1</bIsCompressed>
			<bInGeneric>1</bInGeneric>
		</SoundData>
		<SoundData>
			<SoundID>DIPLO_PEARSON_PEACE_RENAISSANCE_INTRO</SoundID>
			<Filename>Modules/Custom_Civilizations_MCP/Canada/Soundpack/CANADA_PEACE_RENAISSANCE_INTRO</Filename>
			<LoadType>STREAMED</LoadType>
			<bIsCompressed>1</bIsCompressed>
			<bInGeneric>1</bInGeneric>
		</SoundData>
		<SoundData>
			<SoundID>DIPLO_PEARSON_WAR_RENAISSANCE</SoundID>
			<Filename>Modules/Custom_Civilizations_MCP/Canada/Soundpack/CANADA_WAR_RENAISSANCE</Filename>
			<LoadType>STREAMED</LoadType>
			<bIsCompressed>1</bIsCompressed>
			<bInGeneric>1</bInGeneric>
		</SoundData>
		<SoundData>
			<SoundID>DIPLO_PEARSON_WAR_RENAISSANCE_INTRO</SoundID>
			<Filename>Modules/Custom_Civilizations_MCP/Canada/Soundpack/CANADA_WAR_RENAISSANCE_INTRO</Filename>
			<LoadType>STREAMED</LoadType>
			<bIsCompressed>1</bIsCompressed>
			<bInGeneric>1</bInGeneric>
		</SoundData>
		<SoundData>
			<SoundID>DIPLO_PEARSON_PEACE_INDUSTRIAL</SoundID>
			<Filename>Modules/Custom_Civilizations_MCP/Canada/Soundpack/CANADA_PEACE_INDUSTRIAL</Filename>
			<LoadType>STREAMED</LoadType>
			<bIsCompressed>1</bIsCompressed>
			<bInGeneric>1</bInGeneric>
		</SoundData>
		<SoundData>
			<SoundID>DIPLO_PEARSON_PEACE_INDUSTRIAL_INTRO</SoundID>
			<Filename>Modules/Custom_Civilizations_MCP/Canada/Soundpack/CANADA_PEACE_INDUSTRIAL_INTRO</Filename>
			<LoadType>STREAMED</LoadType>
			<bIsCompressed>1</bIsCompressed>
			<bInGeneric>1</bInGeneric>
		</SoundData>
		<SoundData>
			<SoundID>DIPLO_PEARSON_WAR_INDUSTRIAL</SoundID>
			<Filename>Modules/Custom_Civilizations_MCP/Canada/Soundpack/CANADA_WAR_INDUSTRIAL</Filename>
			<LoadType>STREAMED</LoadType>
			<bIsCompressed>1</bIsCompressed>
			<bInGeneric>1</bInGeneric>
		</SoundData>
		<SoundData>
			<SoundID>DIPLO_PEARSON_WAR_INDUSTRIAL_INTRO</SoundID>
			<Filename>Modules/Custom_Civilizations_MCP/Canada/Soundpack/CANADA_WAR_INDUSTRIAL_INTRO</Filename>
			<LoadType>STREAMED</LoadType>
			<bIsCompressed>1</bIsCompressed>
			<bInGeneric>1</bInGeneric>
		</SoundData>
		<SoundData>
			<SoundID>DIPLO_PEARSON_PEACE_MODERN</SoundID>
			<Filename>Modules/Custom_Civilizations_MCP/Canada/Soundpack/CANADA_PEACE_MODERN</Filename>
			<LoadType>STREAMED</LoadType>
			<bIsCompressed>1</bIsCompressed>
			<bInGeneric>1</bInGeneric>
		</SoundData>
		<SoundData>
			<SoundID>DIPLO_PEARSON_PEACE_MODERN_INTRO</SoundID>
			<Filename>Modules/Custom_Civilizations_MCP/Canada/Soundpack/CANADA_PEACE_MODERN_INTRO</Filename>
			<LoadType>STREAMED</LoadType>
			<bIsCompressed>1</bIsCompressed>
			<bInGeneric>1</bInGeneric>
		</SoundData>
		<SoundData>
			<SoundID>DIPLO_PEARSON_WAR_MODERN</SoundID>
			<Filename>Modules/Custom_Civilizations_MCP/Canada/Soundpack/CANADA_WAR_MODERN</Filename>
			<LoadType>STREAMED</LoadType>
			<bIsCompressed>1</bIsCompressed>
			<bInGeneric>1</bInGeneric>
		</SoundData>
		<SoundData>
			<SoundID>DIPLO_PEARSON_WAR_MODERN_INTRO</SoundID>
			<Filename>Modules/Custom_Civilizations_MCP/Canada/Soundpack/CANADA_WAR_MODERN_INTRO</Filename>
			<LoadType>STREAMED</LoadType>
			<bIsCompressed>1</bIsCompressed>
			<bInGeneric>1</bInGeneric>
		</SoundData>
		<SoundData>
			<SoundID>DIPLO_PEARSON_PEACE_FUTURE</SoundID>
			<Filename>Modules/Custom_Civilizations_MCP/Canada/Soundpack/CANADA_PEACE_FUTURE</Filename>
			<LoadType>STREAMED</LoadType>
			<bIsCompressed>1</bIsCompressed>
			<bInGeneric>1</bInGeneric>
		</SoundData>
		<SoundData>
			<SoundID>DIPLO_PEARSON_PEACE_FUTURE_INTRO</SoundID>
			<Filename>Modules/Custom_Civilizations_MCP/Canada/Soundpack/CANADA_PEACE_FUTURE_INTRO</Filename>
			<LoadType>STREAMED</LoadType>
			<bIsCompressed>1</bIsCompressed>
			<bInGeneric>1</bInGeneric>
		</SoundData>
		<SoundData>
			<SoundID>DIPLO_PEARSON_WAR_FUTURE</SoundID>
			<Filename>Modules\Custom_Civilizations\Canada\Soundpack\CANADA_WAR_FUTURE</Filename>
			<LoadType>STREAMED</LoadType>
			<bIsCompressed>1</bIsCompressed>
			<bInGeneric>1</bInGeneric>
		</SoundData>
		<SoundData>
			<SoundID>DIPLO_PEARSON_WAR_FUTURE_INTRO</SoundID>
			<Filename>Modules\Custom_Civilizations\Canada\Soundpack\CANADA_WAR_FUTURE_INTRO</Filename>
			<LoadType>STREAMED</LoadType>
			<bIsCompressed>1</bIsCompressed>
			<bInGeneric>1</bInGeneric>
		</SoundData>
		<SoundData>
			<SoundID>DIPLO_TRUDEAU_EARLY</SoundID>
			<Filename>Modules\Custom_Civilizations\Canada\Soundpack\Trudeau_Early</Filename>
			<LoadType>STREAMED</LoadType>
			<bIsCompressed>1</bIsCompressed>
			<bInGeneric>1</bInGeneric>
		</SoundData>
		<SoundData>
			<SoundID>DIPLO_TRUDEAU_MIDDLE</SoundID>
			<Filename>Modules\Custom_Civilizations\Canada\Soundpack\Trudeau_Middle</Filename>
			<LoadType>STREAMED</LoadType>
			<bIsCompressed>1</bIsCompressed>
			<bInGeneric>1</bInGeneric>
		</SoundData>
		<SoundData>
			<SoundID>DIPLO_TRUDEAU_LATE</SoundID>
			<Filename>Modules\Custom_Civilizations\Canada\Soundpack\Trudeau_Late</Filename>
			<LoadType>STREAMED</LoadType>
			<bIsCompressed>1</bIsCompressed>
			<bInGeneric>1</bInGeneric>
		</SoundData>
	</SoundDatas>
</AudioDefines>
