<?xml version="1.0"?>
<!-- edited with XMLSPY v2004 rel. 2 U (http://www.xmlspy.com) by Dean Ray Johnson (Firaxis Games) -->
<!-- Sid Meier's Civilization 4 -->
<!-- Copyright Firaxis Games 2005 -->
<!-- -->
<!-- AudioDefines -->
<AudioDefines xmlns="x-schema:Ireland_AudioDefinesSchema.xml">
	<SoundDatas>
		<SoundData>
			<SoundID>SND_IRELAND_SELECT</SoundID>
			<Filename>Modules/Custom_Civilizations_MCP/Ireland/SelectOrder/IrishSelect</Filename>
			<LoadType>DYNAMIC_RES</LoadType>
			<bIsCompressed>1</bIsCompressed>
			<bInGeneric>1</bInGeneric>
		</SoundData>
		<SoundData>
			<SoundID>SND_IRELAND_ORDER</SoundID>
			<Filename>Modules/Custom_Civilizations_MCP/Ireland/SelectOrder/IrishOrder</Filename>
			<LoadType>DYNAMIC_RES</LoadType>
			<bIsCompressed>1</bIsCompressed>
			<bInGeneric>1</bInGeneric>
		</SoundData>
		<SoundData>
			<SoundID>DIPLO_BORU_EARLY</SoundID>
			<Filename>Modules/Custom_Civilizations_MCP/Ireland/Soundpack/Boru_Early</Filename>
			<LoadType>STREAMED</LoadType>
			<bIsCompressed>1</bIsCompressed>
			<bInGeneric>1</bInGeneric>
		</SoundData>
		<SoundData>
			<SoundID>DIPLO_BORU_MIDDLE</SoundID>
			<Filename>Modules/Custom_Civilizations_MCP/Ireland/Soundpack/Boru_Middle</Filename>
			<LoadType>STREAMED</LoadType>
			<bIsCompressed>1</bIsCompressed>
			<bInGeneric>1</bInGeneric>
		</SoundData>
		<SoundData>
			<SoundID>DIPLO_BORU_LATE</SoundID>
			<Filename>Modules/Custom_Civilizations_MCP/Ireland/Soundpack/Boru_Late</Filename>
			<LoadType>STREAMED</LoadType>
			<bIsCompressed>1</bIsCompressed>
			<bInGeneric>1</bInGeneric>
		</SoundData>
	</SoundDatas>
</AudioDefines>
