<?xml version='1.0' encoding='UTF-8'?>
<resources>
  <string name="AI_DIPLO_DEMAND_TRIBUTE_POWER_STRONGER_CHARLES_V_1">È ora di pagare il conto, [CT_NAME].</string>
  <string name="AI_DIPLO_FIRST_CONTACT_LEADER_AGAMEMNON_1">Saluti. Sono [OUR_NAME], principe di [OUR_EMPIRE] e defeater di tutti i nemici. Mi dico, sono voi un amico, o nemico?</string>
  <string name="AI_DIPLO_FIRST_CONTACT_LEADER_AHMADINEJAD_1">Salve, [CT_NAME]. La Repubblica Islamica non ha mai minacciato alcun paese nè mai lo farà.</string>
  <string name="AI_DIPLO_FIRST_CONTACT_LEADER_ALARIC_1">Salute! Io sono [OUR_NAME] di [OUR_EMPIRE]. Come dico spesso quando si tratta di dar battaglia \"Quanto più il fieno è fitto, tanto meglio lo si taglia!\".</string>
  <string name="AI_DIPLO_FIRST_CONTACT_LEADER_ALBOIN_1">Che il cielo possa far piovere benedizioni su di te, [CT_NAME]! Io sono [OUR_NAME], benevolo leader dell\'impero [OUR_EMPIRE]! Inondami pure di tributi come preferisci!</string>
  <string name="AI_DIPLO_FIRST_CONTACT_LEADER_ALOOMA_1">Il potente [OUR_EMPIRE] ti saluta. Noi teniamo alla nostra sicurezza, al punto che una donna coperta d\'oro potrebbe camminare con nulla da temere tranne Dio.</string>
  <string name="AI_DIPLO_FIRST_CONTACT_LEADER_AMANISHABHETO_1">Salute, [CT_NAME] di [CT_EMPIRE]. Benvenuto nella terra della ricchezza e della prosperità! Siamo felici di servirti... fintanto che serve a noi.</string>
  <string name="AI_DIPLO_FIRST_CONTACT_LEADER_ANDREA_GRITTI_1">È un onore incontrarti, [CT_NAME]. Spero che le nostre due nazioni riusciranno a vivere in pace e amicizia.</string>
  <string name="AI_DIPLO_FIRST_CONTACT_LEADER_ARPAD_1">Benvenuto nelle mie terre, [CT_NAME]. [OUR_EMPIRE] ti consiglia di non fare il passo più lungo della gamba</string>
  <string name="AI_DIPLO_FIRST_CONTACT_LEADER_BADUR_1">Ah, [CT_NAME]! Benvenuto in [OUR_EMPIRE]! Se s\'è un paradiso sulla terra, è qui, è qui, senza dubbio qui.</string>
  <string name="AI_DIPLO_FIRST_CONTACT_LEADER_BEN_GURION_1">Shalom, [CT_NAME]. Speriamoli portano con voi i rapporti pacifici, dato che posso superare la maggior parte dei ostacoli nel mio senso.</string>
  <string name="AI_DIPLO_FIRST_CONTACT_LEADER_BORU_1">Saluti, [CT_NAME]! Spero che saremo alleati, per il nostro stare insieme, i castelli sono costruiti.</string>
  <string name="AI_DIPLO_FIRST_CONTACT_LEADER_BRIDEI_1">Sono [OUR_NAME] del [OUR_EMPIRE]. Tu chi sei?</string>
  <string name="AI_DIPLO_FIRST_CONTACT_LEADER_BULAN">Saluti! Io sono [OUR_NAME] dell\'[OUR_EMPIRE]. Spero che i nostri due grandi popoli possano vivere in pace.</string>
  <string name="AI_DIPLO_FIRST_CONTACT_LEADER_CANUTE_1">Un caloroso saluto a [CT_EMPIRE]. Io, [OUR_NAME], cerco una pace interiore che supera tutte le dignità della terra ed una coscienza pulita.</string>
  <string name="AI_DIPLO_FIRST_CONTACT_LEADER_CARDENAS_1">Hola! Io sono [OUR_NAME] di [OUR_EMPIRE]. Sono convinto che tutte le buone intenzioni dei governanti semplicemente non bastano e che il fattore collettivo rappresentato dai lavoratori sia indispensabile. Non sei d\'accordo [CT_NAME]? </string>
  <string name="AI_DIPLO_FIRST_CONTACT_LEADER_CASIMIR_1">Salute a te [CT_NAME] di [CT_EMPIRE]. Il fato offre opportunità, ma non tutti sanno coglierle.</string>
  <string name="AI_DIPLO_FIRST_CONTACT_LEADER_CHARLES_XII_1">Sono [OUR_NAME].  Il posto migliore per trovare una mano d\'assistenza è all\'estremità del vostro proprio braccio.</string>
  <string name="AI_DIPLO_FIRST_CONTACT_LEADER_CHE_BONG_NGA_1">Saluti a voi, [CT_NAME]. Sono [OUR_NAME] e gli ricordo che l\'occasione batte ma una volta. Che favori portate con voi?</string>
  <string name="AI_DIPLO_FIRST_CONTACT_LEADER_CHRISTIAN_IV_1">Un caloroso saluto a [CT_EMPIRE]. Io, [OUR_NAME], cerco una pace interiore che supera tutte le dignità della terra ed una coscienza pulita.</string>
  <string name="AI_DIPLO_FIRST_CONTACT_LEADER_CLARK_1">Benvenuto ai [OUR_CIV_SHORT], [CT_NAME]. Noi preferiamo che i nostri campioni siano umili e modesti.</string>
  <string name="AI_DIPLO_FIRST_CONTACT_LEADER_COCHISE_1">Salute! Io sono [OUR_NAME] di [OUR_EMPIRE]. Ti avviso, non accamparti sulle nostre terre o ti combatteremo!</string>
  <string name="AI_DIPLO_FIRST_CONTACT_LEADER_COLLINS_1">Salute, [CT_NAME]! Io sono [OUR_NAME] dei [OUR_CIV_ADJ]. Non saremo dei bersagli immobili, ma delle spine nel fianco se ci minaccerete.</string>
  <string name="AI_DIPLO_FIRST_CONTACT_LEADER_COLOCOLO_1">Attento a te [CT_NAME]. Io sono [OUR_NAME], colui che ti distruggerà!</string>
  <string name="AI_DIPLO_FIRST_CONTACT_LEADER_CUNHAMBEBE_1">Salute, [CT_NAME]! Io sono [OUR_NAME] del popolo [OUR_CIV_ADJ]. Aiutaci a salvare le nostre preziose foreste pluviali ed avrai la nostra eterna gratitudine! </string>
  <string name="AI_DIPLO_FIRST_CONTACT_LEADER_CURTIN_1">Greetings, [CT_NAME]. Il gioco non è perso - o vinto - fino a che l\'ultima flangia non vada.</string>
  <string name="AI_DIPLO_FIRST_CONTACT_LEADER_CUZA_1">Salute! Io sono [OUR_NAME], Signore di [OUR_EMPIRE]! Lasceremo che i nostri popoli vivano in pace o gli orgogliosi discendenti di Geti vi schiacceranno come lombrichi.</string>
  <string name="AI_DIPLO_FIRST_CONTACT_LEADER_DAVID_1">Saluti. Sono [OUR_NAME] e li accolgo favorevolmente, con una mano sul cuore, alla terra di [OUR_CIV_SHORT].</string>
  <string name="AI_DIPLO_FIRST_CONTACT_LEADER_DUFOUR_1">Sono [OUR_NAME], il costruttore di ponti: sia diplomatici che fisici.</string>
  <string name="AI_DIPLO_FIRST_CONTACT_LEADER_DUSAN_1">Saluti, [CT_NAME]. Ricordate, colui che scava una trappola per gli altri e si finisce per se stesso.</string>
  <string name="AI_DIPLO_FIRST_CONTACT_LEADER_ENHEDUANNA_1">Saluti! Io sono [OUR_NAME] dell\'[OUR_EMPIRE]. Spero che i nostri due grandi popoli possano vivere in pace.</string>
  <string name="AI_DIPLO_FIRST_CONTACT_LEADER_FRANZ_1">Salute a te, [CT_NAME]. Lavoriamo fianco a fianco. Si dice che il successo abbia più di un padre.</string>
  <string name="AI_DIPLO_FIRST_CONTACT_LEADER_GJERGJ_KASTRIOTI_1">Possa Dio benedire te e la tua tribù, [CT_NAME]! Accetta la mia ospitalità e celebriamo assieme la pace fra i nostri popoli!</string>
  <string name="AI_DIPLO_FIRST_CONTACT_LEADER_HECTOR_1">Io sono [OUR_NAME] dei [OUR_CIV_SHORT]. Mi attengo a tre regole nella mia vita. Onora gli dei, ama la tua donna, difendi la tua patria.</string>
  <string name="AI_DIPLO_FIRST_CONTACT_LEADER_HIDALGO_1">Possano le benedizioni del Cielo scendere su di te, [CT_NAME]. Io sono [OUR_NAME] dei [OUR_CIV_SHORT]. Messicani, Viva Mexico!</string>
  <string name="AI_DIPLO_FIRST_CONTACT_LEADER_HIRAM_1">Salute. Io sono [OUR_NAME] di [OUR_EMPIRE]. Io sono abituato a lavorare in oro ed in argento, in rame, in ferro, in pietre, ed in legname, ed in porpora, in violaceo, in bisso, ed in iscarlatto; e fare qualunque sorte d’intaglio, e di disegno di qualunque cosa mi sia proposta.</string>
  <string name="AI_DIPLO_FIRST_CONTACT_LEADER_HO_CHI_MINH_1">Ti metto in guarda contro un\'aggressione, [CT_NAME] di [CT_EMPIRE]. Potrete uccidere 10 miei uomini per ognuno dei vostri che io ucciderò. Ma anche
così, voi perderete e io vincerò.</string>
  <string name="AI_DIPLO_FIRST_CONTACT_LEADER_JEZEBEL_1">Sia lode a Baal. Sono [OUR_NAME].</string>
  <string name="AI_DIPLO_FIRST_CONTACT_LEADER_JOGAILA_1">Ciao [CT_NAME]. Spero che si possa aiutare a vicenda, per la persona che dà è la persona che ha.</string>
  <string name="AI_DIPLO_FIRST_CONTACT_LEADER_KAMEHAMEHA_1">Ciao! Mi chiedete qual è la cosa più grande del mondo, vorrei rispondere: E \'la gente, è la gente, è la gente!</string>
  <string name="AI_DIPLO_FIRST_CONTACT_LEADER_KEKKONEN_1">Benvenuto, [CT_NAME] di [CT_EMPIRE]. Una discussione divide, ma la pace costruisce. Costruiamo assieme.</string>
  <string name="AI_DIPLO_FIRST_CONTACT_LEADER_KHOMEINI_1">There is no room for play in Islam, [CT_NAME]. It is deadly serious about everything.</string>
  <string name="AI_DIPLO_FIRST_CONTACT_LEADER_KITRA_1">Saluti, [CT_NAME]. The gods have secured my house and bloodline, have they done the same for you?</string>
  <string name="AI_DIPLO_FIRST_CONTACT_LEADER_LARS_PORSENA_1">Per i Nove Dei, io giuro che la grande casa di Tarquinio non sopporterà più i torti! Saluti, [CT_NAME], Io sono [OUR_NAME] di [OUR_EMPIRE].</string>
  <string name="AI_DIPLO_FIRST_CONTACT_LEADER_LLYWELYN_1">Buon giorno, ho un nome, [OUR_NAME], come il mio impero, [OUR_EMPIRE]. Ho ma due desideri, uno è di essere nella pace con voi. Il secondo è che non dovete mai, di essere disrespectful nella mia presenza.</string>
  <string name="AI_DIPLO_FIRST_CONTACT_LEADER_LORENZO_1">\"Chi vuol esser lieto sia: del doman non v\'è certezza\" Io sono [OUR_NAME] di [OUR_EMPIRE].</string>
  <string name="AI_DIPLO_FIRST_CONTACT_LEADER_MACDONALD_1">Salute! Io sono [OUR_NAME] di [OUR_EMPIRE]. Ti offriamo l\'amicizia della generosa nazione di [OUR_CIV_SHORT]! </string>
  <string name="AI_DIPLO_FIRST_CONTACT_LEADER_MACKENZIEKING_1">Sono [OUR_NAME] e ti offro l\'amicizia di [OUR_EMPIRE]. Dopo tutto, [CT_NAME], quello che conta nel governare è quello che preveniamo, più di quello che facciamo.</string>
  <string name="AI_DIPLO_FIRST_CONTACT_LEADER_MAGNUS_1">La fedeltà è volubile come il favore di un re, [CT_NAME].</string>
  <string name="AI_DIPLO_FIRST_CONTACT_LEADER_MARGRETE_1">Salute, [CT_NAME] di [CT_EMPIRE]. Sono [OUR_NAME] di [OUR_CIV_SHORT], sebbene tu possa chiamarmi \"Margrete, per grazia di Dio figlia di Valdemar Daneking e legittima erede di Danimarca\". Di cosa desideri parlare?</string>
  <string name="AI_DIPLO_FIRST_CONTACT_LEADER_MARIA_THERESA_1">E \'un piacere incontrarvi, [CT_NAME]. È in costante insegnamento della storia, ma non trovano molti alunni, in modo da vicino il mondo che vi circonda.</string>
  <string name="AI_DIPLO_FIRST_CONTACT_LEADER_MARY_STUART_1">Sono [OUR_NAME] di [OUR_EMPIRE]. Essere gentili con tutti, voler bene a molti ed amare pochi, essere necessari e desiderati da coloro che amiamo. Questo è certamente quanto di più simile esista alla felicità, [CT_NAME]. </string>
  <string name="AI_DIPLO_FIRST_CONTACT_LEADER_MASARYK_1">Salute, [CT_NAME]. Sono [OUR_NAME], non temere e non rubare.</string>
  <string name="AI_DIPLO_FIRST_CONTACT_LEADER_MATTHIAS_1">Benvenuti in questa bella terra, [CT_NAME]. Spero che lei portare la pace con voi, per lui che saluta con un bastone, verrà risposto con un club.</string>
  <string name="AI_DIPLO_FIRST_CONTACT_LEADER_MEHAI_1">Salute! Io sono [OUR_NAME], Signore di [OUR_EMPIRE]! Lasceremo che i nostri popoli vivano in pace o gli orgogliosi discendenti di Geti vi schiacceranno come lombrichi.</string>
  <string name="AI_DIPLO_FIRST_CONTACT_LEADER_MINDAUGAS_1">Io, [OUR_NAME], offro l\'amicizia di [CT_EMPIRE]. Una persona che dona è una persona che possiede. Accoglierai questo dono, [CT_NAME]?</string>
  <string name="AI_DIPLO_FIRST_CONTACT_LEADER_NARBONA_1">Ya\'at\'eeh shiyaazh, [CT_NAME]. Cammina sul sentiero dell\'arcobaleno; cammina sul sentiero di una canzone e tutto sarà bellissimo. C\'è una strada che conduce fuori da ogni nebbia, sul sentiero dell\'arcobaleno. Perché segui il sentiero che porta alla nostra terra?</string>
  <string name="AI_DIPLO_FIRST_CONTACT_LEADER_OHIGGINS_1">Salute, [CT_NAME]. Io sono [OUR_NAME], in battaglia sono coraggioso al punto da essere considerato pazzo.</string>
  <string name="AI_DIPLO_FIRST_CONTACT_LEADER_OSTENACO_1">Salute. Io sono [OUR_NAME], Signore di [OUR_EMPIRE]. Un buon capo non prende, ma dà. Sei tu un buon capo, [CT_NAME]?</string>
  <string name="AI_DIPLO_FIRST_CONTACT_LEADER_OWAIN_GLYNDWR_1">Buon giorno, ho un nome, [OUR_NAME]. You shall neither take my, nor my country\'s land.</string>
  <string name="AI_DIPLO_FIRST_CONTACT_LEADER_PEARSON_1">E\' stato spesso troppo facile per i governanti di incitare gli uomini alla guerra, [CT_NAME]. Guidiamo i popoli [CT_CIV_ADJ] e [OUR_CIV_ADJ]  verso una vita di pace assieme.</string>
  <string name="AI_DIPLO_FIRST_CONTACT_LEADER_PEDRO_II_1">Io sono [OUR_NAME] di [OUR_EMPIRE]. Che ne dici di discutere assieme il futuro? Se non si guarda avanti, si rimane indietro.</string>
  <string name="AI_DIPLO_FIRST_CONTACT_LEADER_PERON_1">Salute a te, [CT_NAME]. Un consiglio - se hai la coda di paglia, tienila lontana dal fuoco.</string>
  <string name="AI_DIPLO_FIRST_CONTACT_LEADER_PIYE_1">Il viaggiatore del o di saluti, [OUR_NAME] è il mio nome, benvenuto al [OUR_EMPIRE]. Per favore, far nel paese!</string>
  <string name="AI_DIPLO_FIRST_CONTACT_LEADER_PO_NGBE_1">Benvenuto, [CT_NAME]! Io sono [OUR_NAME] del popolo [OUR_CIV_ADJ]. La mia tranquillità spirituale è sconfinata, la mia pazienza non lo è.</string>
  <string name="AI_DIPLO_FIRST_CONTACT_LEADER_RADAMA_1">Brindiamo ad un futuro migliore, [CT_NAME].</string>
  <string name="AI_DIPLO_FIRST_CONTACT_LEADER_RAJENDRA_1">Ti metto in guarda contro un\'aggressione, [CT_NAME] di [CT_EMPIRE]. Potrete uccidere 10 miei uomini per ognuno dei vostri che io ucciderò. Ma anche
così, voi perderete e io vincerò.</string>
  <string name="AI_DIPLO_FIRST_CONTACT_LEADER_RISHI_1">Saluti! Io sono [OUR_NAME] di [OUR_EMPIRE]. Fai attenzione, io mi avvicino sinuosamente, e con una spinta uccido!</string>
  <string name="AI_DIPLO_FIRST_CONTACT_LEADER_ROBERT_I_1">Auguri! Sono [OUR_NAME]. Ricorda di essere lento e la scelta di un amico, ma più lento a cambiare lui.</string>
  <string name="AI_DIPLO_FIRST_CONTACT_LEADER_SALAMASINA_1">Salve, [CT_NAME] di [CT_CIV_SHORT]. Divertiamoci oggi, perché è stabilito che le nostre vite siano prese dagli dei!</string>
  <string name="AI_DIPLO_FIRST_CONTACT_LEADER_SARGON_1">Saluti! Io sono [OUR_NAME] dell\'[OUR_EMPIRE]. Spero che i nostri due grandi popoli possano vivere in pace.</string>
  <string name="AI_DIPLO_FIRST_CONTACT_LEADER_SATUR_1">Saluti [CT_NAME]. Io sono [OUR_NAME], Re di [OUR_EMPIRE]. Ti fermeresti un po\' ad ammirare la gara di salto del toro?</string>
  <string name="AI_DIPLO_FIRST_CONTACT_LEADER_SHAMBARA_1">J\'espère que nous pourrons porter mutuellement assistance, [CT_NAME], pour les nuits obscures sera de retour après ces quelques nuits clair de lune.</string>
  <string name="AI_DIPLO_FIRST_CONTACT_LEADER_SHAUSHTATAR_1">Saluti, [CT_NAME]. Spero che saremo in molti ci sono pietre che passi a una mela rossa.</string>
  <string name="AI_DIPLO_FIRST_CONTACT_LEADER_SIMEON_I_1">Saluti, [CT_NAME].  Dicami che i vostri amici sono, in modo da posso dire a chi siete.</string>
  <string name="AI_DIPLO_FIRST_CONTACT_LEADER_SOBIESKI_1">Saluti! Sono [OUR_NAME] del [OUR_EMPIRE]. Prima di venire a me, ricordate sempre: nessun lavoro, nessuna panelli.</string>
  <string name="AI_DIPLO_FIRST_CONTACT_LEADER_SONGTSEN_1">Benvenuto, [CT_NAME]. Mi auguro che riusciremo a mantenere relazioni pacifiche, perché le persone eccellenti sono onorate ovunque vadano.</string>
  <string name="AI_DIPLO_FIRST_CONTACT_LEADER_STAMBOLOV_1">Dobro utro [CT_NAME]! Io sono [OUR_NAME] di [OUR_EMPIRE]. Il primo segno di una vera saggezza politica è sempre stato l\'abilità di rinunciare all\'irraggiungibile.</string>
  <string name="AI_DIPLO_FIRST_CONTACT_LEADER_STEPHEN_1">Salute, [CT_NAME] di [CT_EMPIRE]. Siamo forti, perché non ci inorgoglisca la prosperità, né ci abbatta l\'avversità.</string>
  <string name="AI_DIPLO_FIRST_CONTACT_LEADER_SVIATOSLAV_I_1">Greetings, [CT_NAME]. Possa tu stai in guardia: non pasticciare con me, per lui che lecca coltelli presto tagliata la lingua.</string>
  <string name="AI_DIPLO_FIRST_CONTACT_LEADER_TAHARQA_1">Salute, [CT_NAME] del debole [CT_EMPIRE]. Noi tolleriamo la tua presenza su queste terre. Una termite non può fare altro ad una roccia che leccarla.</string>
  <string name="AI_DIPLO_FIRST_CONTACT_LEADER_TEUTA_1">Salve, [CT_NAME]. Io sono [OUR_NAME] di [OUR_EMPIRE]. Ti do il benvenuto, ma sappi che noi così come costruiamo con il sudore, difendiamo con il sangue.</string>
  <string name="AI_DIPLO_FIRST_CONTACT_LEADER_TOMISLAV_1">Salute. Io sono [OUR_NAME] del potente [OUR_EMPIRE]. Aiutiamoci a vicenda, [CT_NAME]. Se le botte sono buone da dare, sono anche buone da ricevere.</string>
  <string name="AI_DIPLO_FIRST_CONTACT_LEADER_TOPILTZIN_1">Osserva, [CT_NAME]! Io sono [OUR_NAME] di [OUR_EMPIRE] - sono qui per volere del Grande Spirito e per la sua volontà sono capo!</string>
  <string name="AI_DIPLO_FIRST_CONTACT_LEADER_TOQUI_LAUTARO_1">Osserva, [CT_NAME]! Io sono [OUR_NAME] di [OUR_EMPIRE] - sono qui per volere del Grande Spirito e per la sua volontà sono capo!</string>
  <string name="AI_DIPLO_FIRST_CONTACT_LEADER_TYMOSHENKO_1">Un vero capo non ha paura quando è sicuro delle sue azioni, [CT_NAME]. Io sono sempre sicuro delle mie azioni. E tu?</string>
  <string name="AI_DIPLO_FIRST_CONTACT_LEADER_VARGAS_1">Saluti, [CT_NAME]. Sono [OUR_NAME].</string>
  <string name="AI_DIPLO_FIRST_CONTACT_LEADER_VITTORIO_EMANUELE_II_1">Saluti! Io sono [OUR_NAME] di [OUR_EMPIRE]. \"Chi la fa l\'aspetti.\" Chi fa del male a qualcuno, si aspetti qualcosa di simile in cambio. Tienilo a mente.</string>
  <string name="AI_DIPLO_FIRST_CONTACT_LEADER_VLAD_1">Salute,  [CT_NAME] di [CT_EMPIRE]. Agisci come parli o parla come agisci, mentre siamo assieme.</string>
  <string name="AI_DIPLO_FIRST_CONTACT_LEADER_WALESA_1">Benvenuto, [CT_NAME]! La libertà non è solo un diritto, ma anche una responsabilità comune ed un dovere.</string>
  <string name="AI_DIPLO_FIRST_CONTACT_LEADER_WENCESLAUS_1">Pazzesco! Altre orde di barbari!</string>
  <string name="AI_DIPLO_FIRST_CONTACT_LEADER_WOVOKA_1">Salute! Io sono [OUR_NAME] di [OUR_EMPIRE]. Il vento aiuta quelli che non hanno un\'ascia per tagliare il legno.</string>
  <string name="AI_DIPLO_FIRST_CONTACT_LEADER_ZIEBEL_1">Saluti, [CT_NAME]. Persone intelligenti sanno di cosa parlano; stolti parlare di quello che già sanno.</string>
</resources>
